pyilz/__init__.py
pyilz/buildings.json
pyilz/calculate_efficiency.py
pyilz/get_blueprints.py
pyilz/get_buildings.py
pyilz/get_device_id.py
pyilz/get_game_state.py
pyilz/get_plots.py
pyilz/get_resources.py
pyilz/get_timers.py
pyilz/get_token.py
pyilz/metadata_to_array.py
pyilz/parse_land.py
pyilz/reference_data.json
pyilz/refresh_token.py
pyilz-0.0.23.dist-info/METADATA
pyilz-0.0.23.dist-info/WHEEL
pyilz-0.0.23.dist-info/licenses/LICENSE
pyilz-0.0.23.dist-info/RECORD
