Metadata-Version: 2.1
Name: pyilz
Version: 0.0.23
Summary: A Python Library for Illuvium Zero Land Management
Project-URL: Homepage, https://github.com/NickJordan289/pyilz
Project-URL: Bug Tracker, https://github.com/NickJordan289/pyilz/issues
Author-email: Nick Jordan <nickjordan289@gmail.com>
License-File: LICENSE
Classifier: License :: OSI Approved :: MIT License
Classifier: Operating System :: Microsoft :: Windows
Classifier: Programming Language :: Python :: 3
Requires-Python: >=3.7
